README.md
setup.cfg
setup.py
baidu_acu_tts/__init__.py
baidu_acu_tts/tts_client.py
baidu_acu_tts/tts_streaming_pb2.py
baidu_acu_tts/tts_streaming_pb2_grpc.py
baidu_acu_tts.egg-info/PKG-INFO
baidu_acu_tts.egg-info/SOURCES.txt
baidu_acu_tts.egg-info/dependency_links.txt
baidu_acu_tts.egg-info/requires.txt
baidu_acu_tts.egg-info/top_level.txt